inputvalidate/__init__.py
inputvalidate/inputvalidate.py
inputvalidate-0.1.8.dist-info/LICENSE
inputvalidate-0.1.8.dist-info/METADATA
inputvalidate-0.1.8.dist-info/WHEEL
inputvalidate-0.1.8.dist-info/top_level.txt
inputvalidate-0.1.8.dist-info/RECORD
