Metadata-Version: 2.1
Name: inputvalidate
Version: 0.1.8
Summary: A Python Library with various functions to validate user input
Author-email: Calvin Chan <calvinchan4370z@gmail.com>
License: MIT License
Project-URL: Homepage, https://github.com/calvin4370/inputvalidate
Project-URL: GitHub, https://github.com/calvin4370/inputvalidate
Project-URL: Issues, https://github.com/calvin4370/inputvalidate/issues
Project-URL: Changelog, https://github.com/calvin4370/inputvalidate/CHANGELOG.md
Keywords: User Input Validation
Classifier: Programming Language :: Python :: 3
Classifier: License :: OSI Approved :: MIT License
Classifier: Operating System :: OS Independent
Requires-Python: >=3.6
License-File: LICENSE
